genderpred_in/__init__.py
genderpred_in/gender_prediction_model.h5
genderpred_in/label_encoder.pickle
genderpred_in/predictLSTM.py
genderpred_in/tokenizer.pickle
genderpred_in-1.0.3.dist-info/LICENSE
genderpred_in-1.0.3.dist-info/METADATA
genderpred_in-1.0.3.dist-info/WHEEL
genderpred_in-1.0.3.dist-info/top_level.txt
genderpred_in-1.0.3.dist-info/RECORD
