Metadata-Version: 2.1
Name: genderpred_in
Version: 1.0.3
Summary: A Package to Predict the Gender of a Person based on their Name (Suited for Indian Names)
Home-page: https://github.com/DhrvM/GenderPred-India
Author: Dhruv Malpani
Author-email: dhruv.malpani2005@gmail.com
Keywords: gender,indian,names,LSTM,tensorflow,keras,classify,prediction
Classifier: Development Status :: 5 - Production/Stable
Classifier: Intended Audience :: Developers
Classifier: Intended Audience :: Financial and Insurance Industry
Classifier: Intended Audience :: Science/Research
Classifier: Operating System :: Microsoft :: Windows
Classifier: Operating System :: MacOS
Classifier: Topic :: Software Development :: Libraries :: Python Modules
Classifier: Topic :: Utilities
Classifier: License :: OSI Approved :: MIT License
Classifier: Programming Language :: Python :: 3.12
Requires-Python: >=3.10
License-File: LICENSE
Requires-Dist: numpy
Requires-Dist: pandas
Requires-Dist: tensorflow
Requires-Dist: keras
Requires-Dist: scikit-learn
